MANIFEST.in
README.md
setup.py
PEAKABOO.egg-info/PKG-INFO
PEAKABOO.egg-info/SOURCES.txt
PEAKABOO.egg-info/dependency_links.txt
PEAKABOO.egg-info/requires.txt
PEAKABOO.egg-info/top_level.txt
peakaboo/__init__.py
peakaboo/__main__.py
peakaboo/data_smoothing.py
peakaboo/feature_visualizer.py
peakaboo/find_peaks.py
peakaboo/kinetics_fitting.py
peakaboo/peak_character.py
peakaboo/peak_classify.py
peakaboo/peak_classify_master.py
peakaboo/peak_finding_master.py
peakaboo/smoothing_visualize.py
peakaboo/version.py
peakaboo/tests/__init__.py
peakaboo/tests/test.csv
peakaboo/tests/test.txt
peakaboo/tests/test_feature_visualizer.py
peakaboo/tests/test_peak_character.py
peakaboo/tests/test_peak_classify.py