Metadata-Version: 1.2
Name: PEAKABOO
Version: 0.14.dev0
Summary: Peakaboo: Feature Analysis in Transient Absorption Spectroscopy
Home-page: http://github.com/liud16/peakaboo
Author: DEMI_IAN_JING
Author-email: demiliu@uw.edu
Maintainer: demi_ian_jing
Maintainer-email: demiliu@uw.edu
License: MIT
Platform: OS Independent
Classifier: Development Status :: 3 - Alpha
Classifier: Environment :: Console
Classifier: Intended Audience :: Science/Research
Classifier: License :: OSI Approved :: MIT License
Classifier: Operating System :: OS Independent
Classifier: Programming Language :: Python
Classifier: Topic :: Scientific/Engineering
Requires: numpy
Requires: scipy
Requires: peakutils
Requires: sklearn
Requires: pandas
Requires: matplotlib
